haps/__init__.py
haps/application.py
haps/config.py
haps/container.py
haps/exceptions.py
haps/scopes/__init__.py
haps/scopes/instance.py
haps/scopes/singleton.py
haps/scopes/thread.py
samples/__init__.py
samples/app_ep.py
samples/instance_properties.py
samples/simple.py
samples/thread_scope.py
samples/autodiscover/__init__.py
samples/autodiscover/sample.py
samples/autodiscover/services/__init__.py
samples/autodiscover/services/bases.py
samples/autodiscover/services/implementations.py
samples/autodiscover/services/deep/__init__.py
samples/autodiscover/services/deep/implementation/__init__.py
samples/autodiscover/services/deep/implementation/extra_pump.py
haps-1.1.3.dist-info/AUTHORS.md
haps-1.1.3.dist-info/LICENSE
haps-1.1.3.dist-info/METADATA
haps-1.1.3.dist-info/WHEEL
haps-1.1.3.dist-info/top_level.txt
haps-1.1.3.dist-info/RECORD
