Metadata-Version: 2.1
Name: haps
Version: 1.1.3
Summary: Simple DI Library
Home-page: https://github.com/ekiro/haps
Author: Piotr Karkut
Author-email: karkucik@gmail.com
License: MIT License
Platform: any
Classifier: License :: OSI Approved :: MIT License
Classifier: Programming Language :: Python
Classifier: Programming Language :: Python :: 3.6
Classifier: Programming Language :: Python :: 3.7
Classifier: Programming Language :: Python :: 3.8
Classifier: Operating System :: OS Independent
Classifier: Topic :: Software Development
Classifier: Intended Audience :: Developers
Classifier: Development Status :: 5 - Production/Stable
License-File: LICENSE
License-File: AUTHORS.md
